doctestcase/__init__.py
doctestcase/__version__.py
doctestcase/case.py
doctestcase/case.pyi
doctestcase/format.py
doctestcase/format.pyi
doctestcase/py.typed
doctestcase-0.2.2.dist-info/METADATA
doctestcase-0.2.2.dist-info/WHEEL
doctestcase-0.2.2.dist-info/licenses/LICENSE
doctestcase-0.2.2.dist-info/RECORD
